benchmarks/__init__.py
benchmarks/chase.py
benchmarks/datalog_frontend.py
benchmarks/relational_algebra_set.py
examples/__init__.py
examples/plot_cbma_spatial_prior.py
examples/plot_load_destrieux_datalog_ir.py
examples/plot_load_destrieux_left_hemisphere_gyri.py
examples/plot_neurosynth_implementation.py
examples_scratch/__init__.py
examples_scratch/new_ns_example.py
examples_scratch/plot_destrieux_queries.py
examples_scratch/plot_load_destrieux_datalog_ir.py
examples_scratch/plot_neurolang_datalog_example-Copy1.py
examples_scratch/problog_ns.py
neurolang/CD_relations.py
neurolang/__init__.py
neurolang/_version.py
neurolang/aabb_tree.py
neurolang/commands.py
neurolang/datalog_chase.py
neurolang/exceptions.py
neurolang/expression_pattern_matching.py
neurolang/expression_walker.py
neurolang/expressions.py
neurolang/interval_algebra.py
neurolang/neurolang.py
neurolang/neurolang_compiler.py
neurolang/perior_tree.py
neurolang/region_solver.py
neurolang/regions.py
neurolang/relational_algebra_provenance.py
neurolang/solver.py
neurolang/typed_symbol_table.py
neurolang/config/__init__.py
neurolang/config/tests/__init__.py
neurolang/config/tests/test_config.py
neurolang/datalog/__init__.py
neurolang/datalog/aggregation.py
neurolang/datalog/basic_representation.py
neurolang/datalog/constraints_representation.py
neurolang/datalog/exceptions.py
neurolang/datalog/expression_processing.py
neurolang/datalog/expressions.py
neurolang/datalog/instance.py
neurolang/datalog/magic_sets.py
neurolang/datalog/negation.py
neurolang/datalog/ontologies_parser.py
neurolang/datalog/ontologies_rewriter.py
neurolang/datalog/translate_to_named_ra.py
neurolang/datalog/wrapped_collections.py
neurolang/datalog/chase/__init__.py
neurolang/datalog/chase/general.py
neurolang/datalog/chase/mgu.py
neurolang/datalog/chase/negation.py
neurolang/datalog/chase/relational_algebra.py
neurolang/datalog/tests/__init__.py
neurolang/datalog/tests/test_aggregation.py
neurolang/datalog/tests/test_chase.py
neurolang-0.1a19.dist-info/AUTHORS.rst
neurolang-0.1a19.dist-info/LICENSE
neurolang-0.1a19.dist-info/METADATA
neurolang-0.1a19.dist-info/WHEEL
neurolang-0.1a19.dist-info/entry_points.txt
neurolang-0.1a19.dist-info/top_level.txt
neurolang-0.1a19.dist-info/RECORD
