Metadata-Version: 2.1
Name: neurolang
Version: 0.1a19
Summary: "NeuroLang: Probabilistic Logic Programming for NeuroScience Research"
Home-page: https://neurolang.github.io
License: BSD 3
Project-URL: Bug Tracker, https://github.com/neurolang/neurolang/issues
Project-URL: Source Code, https://github.com/neurolang/neurolang
Keywords: logic programming,probabilistic logic programming,open world,ontology,neuroscience,neuroimaging,datalog
Classifier: Development Status :: 3 - Alpha
Classifier: Environment :: Console
Classifier: Intended Audience :: Science/Research
Classifier: License :: OSI Approved
Classifier: Operating System :: OS Independent
Classifier: Programming Language :: Python
Classifier: Topic :: Scientific/Engineering
Requires-Python: >=3.7
License-File: LICENSE
License-File: AUTHORS.rst
Requires-Dist: numpy
Requires-Dist: scipy
Requires-Dist: nibabel <5.0.0
Requires-Dist: nilearn <0.9.0,>=0.5.0
Requires-Dist: pandas <2.0.0,>=1.3.5
Requires-Dist: pysdd
Requires-Dist: lark <1.1.3,>=1.1.2
Requires-Dist: scikit-learn
Requires-Dist: matplotlib
Requires-Dist: seaborn
Requires-Dist: typing-inspect
Requires-Dist: rdflib >=6.0.0
Requires-Dist: sqlalchemy <2.0.0
Requires-Dist: pyparsing <3.0.5
Provides-Extra: dev
Requires-Dist: codacy-coverage ; extra == 'dev'
Requires-Dist: pytest <=6.2.5 ; extra == 'dev'
Requires-Dist: pytest-benchmark ; extra == 'dev'
Requires-Dist: pytest-cov ; extra == 'dev'
Requires-Dist: problog ; extra == 'dev'
Requires-Dist: versioneer ; extra == 'dev'
Requires-Dist: tornado ; extra == 'dev'
Requires-Dist: pyyaml ; extra == 'dev'
Provides-Extra: doc
Requires-Dist: sphinx >=4.2.0 ; extra == 'doc'
Requires-Dist: sphinx-bootstrap-theme ; extra == 'doc'
Requires-Dist: sphinx-gallery ; extra == 'doc'
Requires-Dist: numpydoc <1.2.0 ; extra == 'doc'
Provides-Extra: server
Requires-Dist: tornado ; extra == 'server'
Requires-Dist: pyyaml ; extra == 'server'
